<?xml version="1.0" encoding="utf-8"?>
<annotation>
<folder/>
<filename>00000003_jpg.rf.1dc83cf908b24a3ea3e5db984e39fc3f.jpg</filename>
<path>00000003_jpg.rf.1dc83cf908b24a3ea3e5db984e39fc3f.jpg</path>
<source>
<database>roboflow.ai</database>
</source>
<size>
<width>416</width>
<height>416</height>
<depth>3</depth>
</size>
<segmented>0</segmented>
<object>
<name>Mewtwo</name>
<pose>Unspecified</pose>
<truncated>0</truncated>
<difficult>0</difficult>
<occluded>0</occluded>
<bndbox>
<xmin>24</xmin>
<xmax>416</xmax>
<ymin>1</ymin>
<ymax>417</ymax>
</bndbox>
</object>
</annotation>