<?xml version="1.0" encoding="utf-8"?>
<annotation>
<folder/>
<filename>008_Schillok_6_png.rf.3b9f3126616d482545176bfafe453223.jpg</filename>
<path>008_Schillok_6_png.rf.3b9f3126616d482545176bfafe453223.jpg</path>
<source>
<database>roboflow.ai</database>
</source>
<size>
<width>416</width>
<height>416</height>
<depth>3</depth>
</size>
<segmented>0</segmented>
<object>
<name>Wartortle</name>
<pose>Unspecified</pose>
<truncated>0</truncated>
<difficult>0</difficult>
<occluded>0</occluded>
<bndbox>
<xmin>66</xmin>
<xmax>260</xmax>
<ymin>53</ymin>
<ymax>219</ymax>
</bndbox>
</object>
</annotation>