<?xml version="1.0" encoding="utf-8"?>
<annotation>
<folder/>
<filename>1dfdfdd84e5641558bcee36cf8e9bd11_jpg.rf.c4ee96381aa274817c55238722ec3e71.jpg</filename>
<path>1dfdfdd84e5641558bcee36cf8e9bd11_jpg.rf.c4ee96381aa274817c55238722ec3e71.jpg</path>
<source>
<database>roboflow.ai</database>
</source>
<size>
<width>416</width>
<height>416</height>
<depth>3</depth>
</size>
<segmented>0</segmented>
<object>
<name>Gastly</name>
<pose>Unspecified</pose>
<truncated>0</truncated>
<difficult>0</difficult>
<occluded>0</occluded>
<bndbox>
<xmin>37</xmin>
<xmax>359</xmax>
<ymin>65</ymin>
<ymax>338</ymax>
</bndbox>
</object>
</annotation>