<?xml version="1.0" encoding="utf-8"?>
<annotation>
<folder/>
<filename>4b7ea16706c5495fbb8d1c55a4a36a34_jpg.rf.37fff58c59071f18b966452ab15014c3.jpg</filename>
<path>4b7ea16706c5495fbb8d1c55a4a36a34_jpg.rf.37fff58c59071f18b966452ab15014c3.jpg</path>
<source>
<database>roboflow.ai</database>
</source>
<size>
<width>416</width>
<height>416</height>
<depth>3</depth>
</size>
<segmented>0</segmented>
<object>
<name>Mew</name>
<pose>Unspecified</pose>
<truncated>0</truncated>
<difficult>0</difficult>
<occluded>0</occluded>
<bndbox>
<xmin>1</xmin>
<xmax>391</xmax>
<ymin>1</ymin>
<ymax>375</ymax>
</bndbox>
</object>
</annotation>