<?xml version="1.0" encoding="utf-8"?>
<annotation>
<folder/>
<filename>4d59cf582ff1436bbd8556348bf6a362_jpg.rf.7b5c2ff21ec081a24d012300d5486e7d.jpg</filename>
<path>4d59cf582ff1436bbd8556348bf6a362_jpg.rf.7b5c2ff21ec081a24d012300d5486e7d.jpg</path>
<source>
<database>roboflow.ai</database>
</source>
<size>
<width>416</width>
<height>416</height>
<depth>3</depth>
</size>
<segmented>0</segmented>
<object>
<name>Machamp</name>
<pose>Unspecified</pose>
<truncated>0</truncated>
<difficult>0</difficult>
<occluded>0</occluded>
<bndbox>
<xmin>36</xmin>
<xmax>357</xmax>
<ymin>1</ymin>
<ymax>399</ymax>
</bndbox>
</object>
</annotation>