<?xml version="1.0" encoding="utf-8"?>
<annotation>
<folder/>
<filename>5aae97d3b9f446f09819d06568b4a968_jpg.rf.90a4dac1a58295abc2c23e5ba9d1c646.jpg</filename>
<path>5aae97d3b9f446f09819d06568b4a968_jpg.rf.90a4dac1a58295abc2c23e5ba9d1c646.jpg</path>
<source>
<database>roboflow.ai</database>
</source>
<size>
<width>416</width>
<height>416</height>
<depth>3</depth>
</size>
<segmented>0</segmented>
<object>
<name>Nidorina</name>
<pose>Unspecified</pose>
<truncated>0</truncated>
<difficult>0</difficult>
<occluded>0</occluded>
<bndbox>
<xmin>1</xmin>
<xmax>417</xmax>
<ymin>21</ymin>
<ymax>378</ymax>
</bndbox>
</object>
</annotation>