<?xml version="1.0" encoding="utf-8"?>
<annotation>
<folder/>
<filename>5ecb491b17fa45278ced50c25dcecc3f_jpg.rf.3a1e966101ed9f39902178202dc69f28.jpg</filename>
<path>5ecb491b17fa45278ced50c25dcecc3f_jpg.rf.3a1e966101ed9f39902178202dc69f28.jpg</path>
<source>
<database>roboflow.ai</database>
</source>
<size>
<width>416</width>
<height>416</height>
<depth>3</depth>
</size>
<segmented>0</segmented>
<object>
<name>Bulbasaur</name>
<pose>Unspecified</pose>
<truncated>0</truncated>
<difficult>0</difficult>
<occluded>0</occluded>
<bndbox>
<xmin>28</xmin>
<xmax>374</xmax>
<ymin>15</ymin>
<ymax>415</ymax>
</bndbox>
</object>
</annotation>