<?xml version="1.0" encoding="utf-8"?>
<annotation>
<folder/>
<filename>67d7ea38e39b4f3b807a4f57a3013034_jpg.rf.241d5364aba0b412cfe146579931b2fc.jpg</filename>
<path>67d7ea38e39b4f3b807a4f57a3013034_jpg.rf.241d5364aba0b412cfe146579931b2fc.jpg</path>
<source>
<database>roboflow.ai</database>
</source>
<size>
<width>416</width>
<height>416</height>
<depth>3</depth>
</size>
<segmented>0</segmented>
<object>
<name>Blastoise</name>
<pose>Unspecified</pose>
<truncated>0</truncated>
<difficult>0</difficult>
<occluded>0</occluded>
<bndbox>
<xmin>9</xmin>
<xmax>415</xmax>
<ymin>34</ymin>
<ymax>415</ymax>
</bndbox>
</object>
</annotation>