<?xml version="1.0" encoding="utf-8"?>
<annotation>
<folder/>
<filename>6c57bba3252846e0a604aa585eaad7b9_jpg.rf.24bf6ea8251860736af363dbae76f206.jpg</filename>
<path>6c57bba3252846e0a604aa585eaad7b9_jpg.rf.24bf6ea8251860736af363dbae76f206.jpg</path>
<source>
<database>roboflow.ai</database>
</source>
<size>
<width>416</width>
<height>416</height>
<depth>3</depth>
</size>
<segmented>0</segmented>
<object>
<name>Weedle</name>
<pose>Unspecified</pose>
<truncated>0</truncated>
<difficult>0</difficult>
<occluded>0</occluded>
<bndbox>
<xmin>102</xmin>
<xmax>317</xmax>
<ymin>13</ymin>
<ymax>391</ymax>
</bndbox>
</object>
</annotation>