<?xml version="1.0" encoding="utf-8"?>
<annotation>
<folder/>
<filename>79852da5c7f74dc48dc13738a4679f94_jpg.rf.73649f05a530815bb0239d7f27a24e67.jpg</filename>
<path>79852da5c7f74dc48dc13738a4679f94_jpg.rf.73649f05a530815bb0239d7f27a24e67.jpg</path>
<source>
<database>roboflow.ai</database>
</source>
<size>
<width>416</width>
<height>416</height>
<depth>3</depth>
</size>
<segmented>0</segmented>
<object>
<name>Magneton</name>
<pose>Unspecified</pose>
<truncated>0</truncated>
<difficult>0</difficult>
<occluded>0</occluded>
<bndbox>
<xmin>7</xmin>
<xmax>417</xmax>
<ymin>8</ymin>
<ymax>406</ymax>
</bndbox>
</object>
</annotation>