<?xml version="1.0" encoding="utf-8"?>
<annotation>
<folder/>
<filename>93f5fbf9a582479990c719e4f700f18a_jpg.rf.38bc5191120db05c8a58c6b20af9c8d5.jpg</filename>
<path>93f5fbf9a582479990c719e4f700f18a_jpg.rf.38bc5191120db05c8a58c6b20af9c8d5.jpg</path>
<source>
<database>roboflow.ai</database>
</source>
<size>
<width>416</width>
<height>416</height>
<depth>3</depth>
</size>
<segmented>0</segmented>
<object>
<name>Charmeleon</name>
<pose>Unspecified</pose>
<truncated>0</truncated>
<difficult>0</difficult>
<occluded>0</occluded>
<bndbox>
<xmin>23</xmin>
<xmax>382</xmax>
<ymin>1</ymin>
<ymax>416</ymax>
</bndbox>
</object>
</annotation>