<?xml version="1.0" encoding="utf-8"?>
<annotation>
<folder/>
<filename>d906b6b9b24a4baf9c069a27b87e15c0_jpg.rf.a808e44b0c4e79362a85d30d4bcf0ce2.jpg</filename>
<path>d906b6b9b24a4baf9c069a27b87e15c0_jpg.rf.a808e44b0c4e79362a85d30d4bcf0ce2.jpg</path>
<source>
<database>roboflow.ai</database>
</source>
<size>
<width>416</width>
<height>416</height>
<depth>3</depth>
</size>
<segmented>0</segmented>
<object>
<name>Charizard</name>
<pose>Unspecified</pose>
<truncated>0</truncated>
<difficult>0</difficult>
<occluded>0</occluded>
<bndbox>
<xmin>6</xmin>
<xmax>417</xmax>
<ymin>1</ymin>
<ymax>417</ymax>
</bndbox>
</object>
</annotation>